poetry_adv_fun_test/__init__.py
poetry_adv_fun_test/active/__init__.py
poetry_adv_fun_test/active/bjt.py
poetry_adv_fun_test/active/diode.py
poetry_adv_fun_test/active/jfet.py
poetry_adv_fun_test/active/mosfet.py
poetry_adv_fun_test/active/opamp.py
poetry_adv_fun_test/passive/__init__.py
poetry_adv_fun_test/passive/capacitor.py
poetry_adv_fun_test/passive/inductor.py
poetry_adv_fun_test/passive/resistor.py
poetry_adv_fun_test-0.1.6.dist-info/METADATA
poetry_adv_fun_test-0.1.6.dist-info/WHEEL
poetry_adv_fun_test-0.1.6.dist-info/RECORD
