Metadata-Version: 2.4
Name: poetry-adv-fun-test
Version: 0.1.6
Summary: A Python library for modeling active and passive electronic components with test coverage.
License: MIT
Keywords: electronics,devices,poetry,pytest,circuit,components
Author: Sailesh Mishra
Author-email: saileshmishra164@gmail.com
Requires-Python: >=3.10,<4.0
Classifier: License :: OSI Approved :: MIT License
Classifier: Programming Language :: Python :: 3
Classifier: Programming Language :: Python :: 3.10
Classifier: Programming Language :: Python :: 3.11
Classifier: Programming Language :: Python :: 3.12
Classifier: Programming Language :: Python :: 3.13
Classifier: Programming Language :: Python :: 3.14
Project-URL: Homepage, https://github.com/saileshmishraindia/poetry-device-lib-testing
Project-URL: Repository, https://github.com/saileshmishraindia/poetry-device-lib-testing
